{"country":"PK","years":{"2026":[{"date":"2026-02-05","name":"Kashmir Solidarity Day","subdivisions":[]},{"date":"2026-03-20","name":"Eid al-Fitr (estimated)","subdivisions":[]},{"date":"2026-03-21","name":"Eid al-Fitr (estimated)","subdivisions":[]},{"date":"2026-03-22","name":"Eid al-Fitr (estimated)","subdivisions":[]},{"date":"2026-03-23","name":"Pakistan Day","subdivisions":[]},{"date":"2026-05-01","name":"Labor Day","subdivisions":[]},{"date":"2026-05-27","name":"Eid al-Adha (estimated)","subdivisions":[]},{"date":"2026-05-28","name":"Eid al-Adha (estimated); Youm-e-Takbeer","subdivisions":[]},{"date":"2026-05-29","name":"Eid al-Adha (estimated)","subdivisions":[]},{"date":"2026-06-24","name":"Ashura (estimated)","subdivisions":[]},{"date":"2026-06-25","name":"Ashura (estimated)","subdivisions":[]},{"date":"2026-08-14","name":"Independence Day","subdivisions":[]},{"date":"2026-08-25","name":"Prophet's Birthday (estimated)","subdivisions":[]},{"date":"2026-11-09","name":"Iqbal Day","subdivisions":[]},{"date":"2026-12-25","name":"Quaid-e-Azam Day","subdivisions":[]}],"2027":[{"date":"2027-02-05","name":"Kashmir Solidarity Day","subdivisions":[]},{"date":"2027-03-09","name":"Eid al-Fitr (estimated)","subdivisions":[]},{"date":"2027-03-10","name":"Eid al-Fitr (estimated)","subdivisions":[]},{"date":"2027-03-11","name":"Eid al-Fitr (estimated)","subdivisions":[]},{"date":"2027-03-23","name":"Pakistan Day","subdivisions":[]},{"date":"2027-05-01","name":"Labor Day","subdivisions":[]},{"date":"2027-05-16","name":"Eid al-Adha (estimated)","subdivisions":[]},{"date":"2027-05-17","name":"Eid al-Adha (estimated)","subdivisions":[]},{"date":"2027-05-18","name":"Eid al-Adha (estimated)","subdivisions":[]},{"date":"2027-05-28","name":"Youm-e-Takbeer","subdivisions":[]},{"date":"2027-06-14","name":"Ashura (estimated)","subdivisions":[]},{"date":"2027-06-15","name":"Ashura (estimated)","subdivisions":[]},{"date":"2027-08-14","name":"Independence Day; Prophet's Birthday (estimated)","subdivisions":[]},{"date":"2027-11-09","name":"Iqbal Day","subdivisions":[]},{"date":"2027-12-25","name":"Quaid-e-Azam Day","subdivisions":[]}],"2028":[{"date":"2028-02-05","name":"Kashmir Solidarity Day","subdivisions":[]},{"date":"2028-02-26","name":"Eid al-Fitr (estimated)","subdivisions":[]},{"date":"2028-02-27","name":"Eid al-Fitr (estimated)","subdivisions":[]},{"date":"2028-02-28","name":"Eid al-Fitr (estimated)","subdivisions":[]},{"date":"2028-03-23","name":"Pakistan Day","subdivisions":[]},{"date":"2028-05-01","name":"Labor Day","subdivisions":[]},{"date":"2028-05-05","name":"Eid al-Adha (estimated)","subdivisions":[]},{"date":"2028-05-06","name":"Eid al-Adha (estimated)","subdivisions":[]},{"date":"2028-05-07","name":"Eid al-Adha (estimated)","subdivisions":[]},{"date":"2028-05-28","name":"Youm-e-Takbeer","subdivisions":[]},{"date":"2028-06-02","name":"Ashura (estimated)","subdivisions":[]},{"date":"2028-06-03","name":"Ashura (estimated)","subdivisions":[]},{"date":"2028-08-03","name":"Prophet's Birthday (estimated)","subdivisions":[]},{"date":"2028-08-14","name":"Independence Day","subdivisions":[]},{"date":"2028-11-09","name":"Iqbal Day","subdivisions":[]},{"date":"2028-12-25","name":"Quaid-e-Azam Day","subdivisions":[]}],"2029":[{"date":"2029-02-05","name":"Kashmir Solidarity Day","subdivisions":[]},{"date":"2029-02-14","name":"Eid al-Fitr (estimated)","subdivisions":[]},{"date":"2029-02-15","name":"Eid al-Fitr (estimated)","subdivisions":[]},{"date":"2029-02-16","name":"Eid al-Fitr (estimated)","subdivisions":[]},{"date":"2029-03-23","name":"Pakistan Day","subdivisions":[]},{"date":"2029-04-24","name":"Eid al-Adha (estimated)","subdivisions":[]},{"date":"2029-04-25","name":"Eid al-Adha (estimated)","subdivisions":[]},{"date":"2029-04-26","name":"Eid al-Adha (estimated)","subdivisions":[]},{"date":"2029-05-01","name":"Labor Day","subdivisions":[]},{"date":"2029-05-22","name":"Ashura (estimated)","subdivisions":[]},{"date":"2029-05-23","name":"Ashura (estimated)","subdivisions":[]},{"date":"2029-05-28","name":"Youm-e-Takbeer","subdivisions":[]},{"date":"2029-07-24","name":"Prophet's Birthday (estimated)","subdivisions":[]},{"date":"2029-08-14","name":"Independence Day","subdivisions":[]},{"date":"2029-11-09","name":"Iqbal Day","subdivisions":[]},{"date":"2029-12-25","name":"Quaid-e-Azam Day","subdivisions":[]}],"2030":[{"date":"2030-02-04","name":"Eid al-Fitr (estimated)","subdivisions":[]},{"date":"2030-02-05","name":"Eid al-Fitr (estimated); Kashmir Solidarity Day","subdivisions":[]},{"date":"2030-02-06","name":"Eid al-Fitr (estimated)","subdivisions":[]},{"date":"2030-03-23","name":"Pakistan Day","subdivisions":[]},{"date":"2030-04-13","name":"Eid al-Adha (estimated)","subdivisions":[]},{"date":"2030-04-14","name":"Eid al-Adha (estimated)","subdivisions":[]},{"date":"2030-04-15","name":"Eid al-Adha (estimated)","subdivisions":[]},{"date":"2030-05-01","name":"Labor Day","subdivisions":[]},{"date":"2030-05-11","name":"Ashura (estimated)","subdivisions":[]},{"date":"2030-05-12","name":"Ashura (estimated)","subdivisions":[]},{"date":"2030-05-28","name":"Youm-e-Takbeer","subdivisions":[]},{"date":"2030-07-13","name":"Prophet's Birthday (estimated)","subdivisions":[]},{"date":"2030-08-14","name":"Independence Day","subdivisions":[]},{"date":"2030-11-09","name":"Iqbal Day","subdivisions":[]},{"date":"2030-12-25","name":"Quaid-e-Azam Day","subdivisions":[]}],"2031":[{"date":"2031-01-24","name":"Eid al-Fitr (estimated)","subdivisions":[]},{"date":"2031-01-25","name":"Eid al-Fitr (estimated)","subdivisions":[]},{"date":"2031-01-26","name":"Eid al-Fitr (estimated)","subdivisions":[]},{"date":"2031-02-05","name":"Kashmir Solidarity Day","subdivisions":[]},{"date":"2031-03-23","name":"Pakistan Day","subdivisions":[]},{"date":"2031-04-02","name":"Eid al-Adha (estimated)","subdivisions":[]},{"date":"2031-04-03","name":"Eid al-Adha (estimated)","subdivisions":[]},{"date":"2031-04-04","name":"Eid al-Adha (estimated)","subdivisions":[]},{"date":"2031-05-01","name":"Ashura (estimated); Labor Day","subdivisions":[]},{"date":"2031-05-02","name":"Ashura (estimated)","subdivisions":[]},{"date":"2031-05-28","name":"Youm-e-Takbeer","subdivisions":[]},{"date":"2031-07-02","name":"Prophet's Birthday (estimated)","subdivisions":[]},{"date":"2031-08-14","name":"Independence Day","subdivisions":[]},{"date":"2031-11-09","name":"Iqbal Day","subdivisions":[]},{"date":"2031-12-25","name":"Quaid-e-Azam Day","subdivisions":[]}],"2032":[{"date":"2032-01-14","name":"Eid al-Fitr (estimated)","subdivisions":[]},{"date":"2032-01-15","name":"Eid al-Fitr (estimated)","subdivisions":[]},{"date":"2032-01-16","name":"Eid al-Fitr (estimated)","subdivisions":[]},{"date":"2032-02-05","name":"Kashmir Solidarity Day","subdivisions":[]},{"date":"2032-03-22","name":"Eid al-Adha (estimated)","subdivisions":[]},{"date":"2032-03-23","name":"Eid al-Adha (estimated); Pakistan Day","subdivisions":[]},{"date":"2032-03-24","name":"Eid al-Adha (estimated)","subdivisions":[]},{"date":"2032-04-19","name":"Ashura (estimated)","subdivisions":[]},{"date":"2032-04-20","name":"Ashura (estimated)","subdivisions":[]},{"date":"2032-05-01","name":"Labor Day","subdivisions":[]},{"date":"2032-05-28","name":"Youm-e-Takbeer","subdivisions":[]},{"date":"2032-06-20","name":"Prophet's Birthday (estimated)","subdivisions":[]},{"date":"2032-08-14","name":"Independence Day","subdivisions":[]},{"date":"2032-11-09","name":"Iqbal Day","subdivisions":[]},{"date":"2032-12-25","name":"Quaid-e-Azam Day","subdivisions":[]}],"2033":[{"date":"2033-01-02","name":"Eid al-Fitr (estimated)","subdivisions":[]},{"date":"2033-01-03","name":"Eid al-Fitr (estimated)","subdivisions":[]},{"date":"2033-01-04","name":"Eid al-Fitr (estimated)","subdivisions":[]},{"date":"2033-02-05","name":"Kashmir Solidarity Day","subdivisions":[]},{"date":"2033-03-11","name":"Eid al-Adha (estimated)","subdivisions":[]},{"date":"2033-03-12","name":"Eid al-Adha (estimated)","subdivisions":[]},{"date":"2033-03-13","name":"Eid al-Adha (estimated)","subdivisions":[]},{"date":"2033-03-23","name":"Pakistan Day","subdivisions":[]},{"date":"2033-04-09","name":"Ashura (estimated)","subdivisions":[]},{"date":"2033-04-10","name":"Ashura (estimated)","subdivisions":[]},{"date":"2033-05-01","name":"Labor Day","subdivisions":[]},{"date":"2033-05-28","name":"Youm-e-Takbeer","subdivisions":[]},{"date":"2033-06-09","name":"Prophet's Birthday (estimated)","subdivisions":[]},{"date":"2033-08-14","name":"Independence Day","subdivisions":[]},{"date":"2033-11-09","name":"Iqbal Day","subdivisions":[]},{"date":"2033-12-23","name":"Eid al-Fitr (estimated)","subdivisions":[]},{"date":"2033-12-24","name":"Eid al-Fitr (estimated)","subdivisions":[]},{"date":"2033-12-25","name":"Eid al-Fitr (estimated); Quaid-e-Azam Day","subdivisions":[]}],"2034":[{"date":"2034-02-05","name":"Kashmir Solidarity Day","subdivisions":[]},{"date":"2034-03-01","name":"Eid al-Adha (estimated)","subdivisions":[]},{"date":"2034-03-02","name":"Eid al-Adha (estimated)","subdivisions":[]},{"date":"2034-03-03","name":"Eid al-Adha (estimated)","subdivisions":[]},{"date":"2034-03-23","name":"Pakistan Day","subdivisions":[]},{"date":"2034-03-29","name":"Ashura (estimated)","subdivisions":[]},{"date":"2034-03-30","name":"Ashura (estimated)","subdivisions":[]},{"date":"2034-05-01","name":"Labor Day","subdivisions":[]},{"date":"2034-05-28","name":"Youm-e-Takbeer","subdivisions":[]},{"date":"2034-05-30","name":"Prophet's Birthday (estimated)","subdivisions":[]},{"date":"2034-08-14","name":"Independence Day","subdivisions":[]},{"date":"2034-11-09","name":"Iqbal Day","subdivisions":[]},{"date":"2034-12-12","name":"Eid al-Fitr (estimated)","subdivisions":[]},{"date":"2034-12-13","name":"Eid al-Fitr (estimated)","subdivisions":[]},{"date":"2034-12-14","name":"Eid al-Fitr (estimated)","subdivisions":[]},{"date":"2034-12-25","name":"Quaid-e-Azam Day","subdivisions":[]}],"2035":[{"date":"2035-02-05","name":"Kashmir Solidarity Day","subdivisions":[]},{"date":"2035-02-18","name":"Eid al-Adha (estimated)","subdivisions":[]},{"date":"2035-02-19","name":"Eid al-Adha (estimated)","subdivisions":[]},{"date":"2035-02-20","name":"Eid al-Adha (estimated)","subdivisions":[]},{"date":"2035-03-19","name":"Ashura (estimated)","subdivisions":[]},{"date":"2035-03-20","name":"Ashura (estimated)","subdivisions":[]},{"date":"2035-03-23","name":"Pakistan Day","subdivisions":[]},{"date":"2035-05-01","name":"Labor Day","subdivisions":[]},{"date":"2035-05-20","name":"Prophet's Birthday (estimated)","subdivisions":[]},{"date":"2035-05-28","name":"Youm-e-Takbeer","subdivisions":[]},{"date":"2035-08-14","name":"Independence Day","subdivisions":[]},{"date":"2035-11-09","name":"Iqbal Day","subdivisions":[]},{"date":"2035-12-01","name":"Eid al-Fitr (estimated)","subdivisions":[]},{"date":"2035-12-02","name":"Eid al-Fitr (estimated)","subdivisions":[]},{"date":"2035-12-03","name":"Eid al-Fitr (estimated)","subdivisions":[]},{"date":"2035-12-25","name":"Quaid-e-Azam Day","subdivisions":[]}],"2036":[{"date":"2036-02-05","name":"Kashmir Solidarity Day","subdivisions":[]},{"date":"2036-02-07","name":"Eid al-Adha (estimated)","subdivisions":[]},{"date":"2036-02-08","name":"Eid al-Adha (estimated)","subdivisions":[]},{"date":"2036-02-09","name":"Eid al-Adha (estimated)","subdivisions":[]},{"date":"2036-03-07","name":"Ashura (estimated)","subdivisions":[]},{"date":"2036-03-08","name":"Ashura (estimated)","subdivisions":[]},{"date":"2036-03-23","name":"Pakistan Day","subdivisions":[]},{"date":"2036-05-01","name":"Labor Day","subdivisions":[]},{"date":"2036-05-08","name":"Prophet's Birthday (estimated)","subdivisions":[]},{"date":"2036-05-28","name":"Youm-e-Takbeer","subdivisions":[]},{"date":"2036-08-14","name":"Independence Day","subdivisions":[]},{"date":"2036-11-09","name":"Iqbal Day","subdivisions":[]},{"date":"2036-11-19","name":"Eid al-Fitr (estimated)","subdivisions":[]},{"date":"2036-11-20","name":"Eid al-Fitr (estimated)","subdivisions":[]},{"date":"2036-11-21","name":"Eid al-Fitr (estimated)","subdivisions":[]},{"date":"2036-12-25","name":"Quaid-e-Azam Day","subdivisions":[]}],"2037":[{"date":"2037-01-26","name":"Eid al-Adha (estimated)","subdivisions":[]},{"date":"2037-01-27","name":"Eid al-Adha (estimated)","subdivisions":[]},{"date":"2037-01-28","name":"Eid al-Adha (estimated)","subdivisions":[]},{"date":"2037-02-05","name":"Kashmir Solidarity Day","subdivisions":[]},{"date":"2037-02-24","name":"Ashura (estimated)","subdivisions":[]},{"date":"2037-02-25","name":"Ashura (estimated)","subdivisions":[]},{"date":"2037-03-23","name":"Pakistan Day","subdivisions":[]},{"date":"2037-04-28","name":"Prophet's Birthday (estimated)","subdivisions":[]},{"date":"2037-05-01","name":"Labor Day","subdivisions":[]},{"date":"2037-05-28","name":"Youm-e-Takbeer","subdivisions":[]},{"date":"2037-08-14","name":"Independence Day","subdivisions":[]},{"date":"2037-11-08","name":"Eid al-Fitr (estimated)","subdivisions":[]},{"date":"2037-11-09","name":"Eid al-Fitr (estimated); Iqbal Day","subdivisions":[]},{"date":"2037-11-10","name":"Eid al-Fitr (estimated)","subdivisions":[]},{"date":"2037-12-25","name":"Quaid-e-Azam Day","subdivisions":[]}],"2038":[{"date":"2038-01-16","name":"Eid al-Adha (estimated)","subdivisions":[]},{"date":"2038-01-17","name":"Eid al-Adha (estimated)","subdivisions":[]},{"date":"2038-01-18","name":"Eid al-Adha (estimated)","subdivisions":[]},{"date":"2038-02-05","name":"Kashmir Solidarity Day","subdivisions":[]},{"date":"2038-02-13","name":"Ashura (estimated)","subdivisions":[]},{"date":"2038-02-14","name":"Ashura (estimated)","subdivisions":[]},{"date":"2038-03-23","name":"Pakistan Day","subdivisions":[]},{"date":"2038-04-17","name":"Prophet's Birthday (estimated)","subdivisions":[]},{"date":"2038-05-01","name":"Labor Day","subdivisions":[]},{"date":"2038-05-28","name":"Youm-e-Takbeer","subdivisions":[]},{"date":"2038-08-14","name":"Independence Day","subdivisions":[]},{"date":"2038-10-29","name":"Eid al-Fitr (estimated)","subdivisions":[]},{"date":"2038-10-30","name":"Eid al-Fitr (estimated)","subdivisions":[]},{"date":"2038-10-31","name":"Eid al-Fitr (estimated)","subdivisions":[]},{"date":"2038-11-09","name":"Iqbal Day","subdivisions":[]},{"date":"2038-12-25","name":"Quaid-e-Azam Day","subdivisions":[]}],"2039":[{"date":"2039-01-05","name":"Eid al-Adha (estimated)","subdivisions":[]},{"date":"2039-01-06","name":"Eid al-Adha (estimated)","subdivisions":[]},{"date":"2039-01-07","name":"Eid al-Adha (estimated)","subdivisions":[]},{"date":"2039-02-03","name":"Ashura (estimated)","subdivisions":[]},{"date":"2039-02-04","name":"Ashura (estimated)","subdivisions":[]},{"date":"2039-02-05","name":"Kashmir Solidarity Day","subdivisions":[]},{"date":"2039-03-23","name":"Pakistan Day","subdivisions":[]},{"date":"2039-04-06","name":"Prophet's Birthday (estimated)","subdivisions":[]},{"date":"2039-05-01","name":"Labor Day","subdivisions":[]},{"date":"2039-05-28","name":"Youm-e-Takbeer","subdivisions":[]},{"date":"2039-08-14","name":"Independence Day","subdivisions":[]},{"date":"2039-10-19","name":"Eid al-Fitr (estimated)","subdivisions":[]},{"date":"2039-10-20","name":"Eid al-Fitr (estimated)","subdivisions":[]},{"date":"2039-10-21","name":"Eid al-Fitr (estimated)","subdivisions":[]},{"date":"2039-11-09","name":"Iqbal Day","subdivisions":[]},{"date":"2039-12-25","name":"Quaid-e-Azam Day","subdivisions":[]},{"date":"2039-12-26","name":"Eid al-Adha (estimated)","subdivisions":[]},{"date":"2039-12-27","name":"Eid al-Adha (estimated)","subdivisions":[]},{"date":"2039-12-28","name":"Eid al-Adha (estimated)","subdivisions":[]}],"2040":[{"date":"2040-01-23","name":"Ashura (estimated)","subdivisions":[]},{"date":"2040-01-24","name":"Ashura (estimated)","subdivisions":[]},{"date":"2040-02-05","name":"Kashmir Solidarity Day","subdivisions":[]},{"date":"2040-03-23","name":"Pakistan Day","subdivisions":[]},{"date":"2040-03-25","name":"Prophet's Birthday (estimated)","subdivisions":[]},{"date":"2040-05-01","name":"Labor Day","subdivisions":[]},{"date":"2040-05-28","name":"Youm-e-Takbeer","subdivisions":[]},{"date":"2040-08-14","name":"Independence Day","subdivisions":[]},{"date":"2040-10-07","name":"Eid al-Fitr (estimated)","subdivisions":[]},{"date":"2040-10-08","name":"Eid al-Fitr (estimated)","subdivisions":[]},{"date":"2040-10-09","name":"Eid al-Fitr (estimated)","subdivisions":[]},{"date":"2040-11-09","name":"Iqbal Day","subdivisions":[]},{"date":"2040-12-14","name":"Eid al-Adha (estimated)","subdivisions":[]},{"date":"2040-12-15","name":"Eid al-Adha (estimated)","subdivisions":[]},{"date":"2040-12-16","name":"Eid al-Adha (estimated)","subdivisions":[]},{"date":"2040-12-25","name":"Quaid-e-Azam Day","subdivisions":[]}],"2041":[{"date":"2041-01-12","name":"Ashura (estimated)","subdivisions":[]},{"date":"2041-01-13","name":"Ashura (estimated)","subdivisions":[]},{"date":"2041-02-05","name":"Kashmir Solidarity Day","subdivisions":[]},{"date":"2041-03-15","name":"Prophet's Birthday (estimated)","subdivisions":[]},{"date":"2041-03-23","name":"Pakistan Day","subdivisions":[]},{"date":"2041-05-01","name":"Labor Day","subdivisions":[]},{"date":"2041-05-28","name":"Youm-e-Takbeer","subdivisions":[]},{"date":"2041-08-14","name":"Independence Day","subdivisions":[]},{"date":"2041-09-26","name":"Eid al-Fitr (estimated)","subdivisions":[]},{"date":"2041-09-27","name":"Eid al-Fitr (estimated)","subdivisions":[]},{"date":"2041-09-28","name":"Eid al-Fitr (estimated)","subdivisions":[]},{"date":"2041-11-09","name":"Iqbal Day","subdivisions":[]},{"date":"2041-12-04","name":"Eid al-Adha (estimated)","subdivisions":[]},{"date":"2041-12-05","name":"Eid al-Adha (estimated)","subdivisions":[]},{"date":"2041-12-06","name":"Eid al-Adha (estimated)","subdivisions":[]},{"date":"2041-12-25","name":"Quaid-e-Azam Day","subdivisions":[]}],"2042":[{"date":"2042-01-01","name":"Ashura (estimated)","subdivisions":[]},{"date":"2042-01-02","name":"Ashura (estimated)","subdivisions":[]},{"date":"2042-02-05","name":"Kashmir Solidarity Day","subdivisions":[]},{"date":"2042-03-04","name":"Prophet's Birthday (estimated)","subdivisions":[]},{"date":"2042-03-23","name":"Pakistan Day","subdivisions":[]},{"date":"2042-05-01","name":"Labor Day","subdivisions":[]},{"date":"2042-05-28","name":"Youm-e-Takbeer","subdivisions":[]},{"date":"2042-08-14","name":"Independence Day","subdivisions":[]},{"date":"2042-09-15","name":"Eid al-Fitr (estimated)","subdivisions":[]},{"date":"2042-09-16","name":"Eid al-Fitr (estimated)","subdivisions":[]},{"date":"2042-09-17","name":"Eid al-Fitr (estimated)","subdivisions":[]},{"date":"2042-11-09","name":"Iqbal Day","subdivisions":[]},{"date":"2042-11-23","name":"Eid al-Adha (estimated)","subdivisions":[]},{"date":"2042-11-24","name":"Eid al-Adha (estimated)","subdivisions":[]},{"date":"2042-11-25","name":"Eid al-Adha (estimated)","subdivisions":[]},{"date":"2042-12-22","name":"Ashura (estimated)","subdivisions":[]},{"date":"2042-12-23","name":"Ashura (estimated)","subdivisions":[]},{"date":"2042-12-25","name":"Quaid-e-Azam Day","subdivisions":[]}],"2043":[{"date":"2043-02-05","name":"Kashmir Solidarity Day","subdivisions":[]},{"date":"2043-02-22","name":"Prophet's Birthday (estimated)","subdivisions":[]},{"date":"2043-03-23","name":"Pakistan Day","subdivisions":[]},{"date":"2043-05-01","name":"Labor Day","subdivisions":[]},{"date":"2043-05-28","name":"Youm-e-Takbeer","subdivisions":[]},{"date":"2043-08-14","name":"Independence Day","subdivisions":[]},{"date":"2043-09-04","name":"Eid al-Fitr (estimated)","subdivisions":[]},{"date":"2043-09-05","name":"Eid al-Fitr (estimated)","subdivisions":[]},{"date":"2043-09-06","name":"Eid al-Fitr (estimated)","subdivisions":[]},{"date":"2043-11-09","name":"Iqbal Day","subdivisions":[]},{"date":"2043-11-12","name":"Eid al-Adha (estimated)","subdivisions":[]},{"date":"2043-11-13","name":"Eid al-Adha (estimated)","subdivisions":[]},{"date":"2043-11-14","name":"Eid al-Adha (estimated)","subdivisions":[]},{"date":"2043-12-11","name":"Ashura (estimated)","subdivisions":[]},{"date":"2043-12-12","name":"Ashura (estimated)","subdivisions":[]},{"date":"2043-12-25","name":"Quaid-e-Azam Day","subdivisions":[]}],"2044":[{"date":"2044-02-05","name":"Kashmir Solidarity Day","subdivisions":[]},{"date":"2044-02-11","name":"Prophet's Birthday (estimated)","subdivisions":[]},{"date":"2044-03-23","name":"Pakistan Day","subdivisions":[]},{"date":"2044-05-01","name":"Labor Day","subdivisions":[]},{"date":"2044-05-28","name":"Youm-e-Takbeer","subdivisions":[]},{"date":"2044-08-14","name":"Independence Day","subdivisions":[]},{"date":"2044-08-24","name":"Eid al-Fitr (estimated)","subdivisions":[]},{"date":"2044-08-25","name":"Eid al-Fitr (estimated)","subdivisions":[]},{"date":"2044-08-26","name":"Eid al-Fitr (estimated)","subdivisions":[]},{"date":"2044-10-31","name":"Eid al-Adha (estimated)","subdivisions":[]},{"date":"2044-11-01","name":"Eid al-Adha (estimated)","subdivisions":[]},{"date":"2044-11-02","name":"Eid al-Adha (estimated)","subdivisions":[]},{"date":"2044-11-09","name":"Iqbal Day","subdivisions":[]},{"date":"2044-11-29","name":"Ashura (estimated)","subdivisions":[]},{"date":"2044-11-30","name":"Ashura (estimated)","subdivisions":[]},{"date":"2044-12-25","name":"Quaid-e-Azam Day","subdivisions":[]}]}}